pyapp_window/__init__.py
pyapp_window/__main__.py
pyapp_window/backend.py
pyapp_window/favicon.svg
pyapp_window/launcher.py
pyapp_window/opener.py
pyapp_window/process.py
pyapp_window/util.py
pyapp_window/webview_window/__init__.py
pyapp_window/webview_window/api.py
pyapp_window/webview_window/backend_implementations/__init__.py
pyapp_window/webview_window/backend_implementations/_base.py
pyapp_window/webview_window/backend_implementations/chrome_appmode.py
pyapp_window/webview_window/backend_implementations/pywebview.py
pyapp_window/webview_window/backend_implementations/toga.py
pyapp_window/webview_window/backend_implementations/webbrowser.py
pyapp_window/webview_window/backend_implementations/wxpython.py
pyapp_window/webview_window/util.py
pyapp_window-2.1.3.dist-info/LICENSE
pyapp_window-2.1.3.dist-info/METADATA
pyapp_window-2.1.3.dist-info/WHEEL
pyapp_window-2.1.3.dist-info/RECORD
